{
  "_format": "hh-sol-cache-2",
  "files": {
    "C:\\Users\\Samarth Saxena\\Desktop\\Vasu\\Code\\zk-fundraiser\\hardhat\\contracts\\ZkFundraiser.sol": {
      "lastModificationDate": 1680620207007,
      "contentHash": "20eeb51a5e2f02b52345004c09998212",
      "sourceName": "contracts/ZkFundraiser.sol",
      "solcConfig": {
        "version": "0.8.18",
        "settings": {
          "optimizer": {
            "enabled": false,
            "runs": 200
          },
          "outputSelection": {
            "*": {
              "*": [
                "abi",
                "evm.bytecode",
                "evm.deployedBytecode",
                "evm.methodIdentifiers",
                "metadata",
                "devdoc",
                "userdoc",
                "storageLayout",
                "evm.gasEstimates"
              ],
              "": [
                "ast"
              ]
            }
          },
          "metadata": {
            "useLiteralContent": true
          }
        }
      },
      "imports": [],
      "versionPragmas": [
        "^0.8.18"
      ],
      "artifacts": [
        "ZkFundraiser"
      ]
    }
  }
}
